klimalogger/__init__.py
klimalogger/calc/__init__.py
klimalogger/calc/pressure.py
klimalogger/calc/temperature.py
klimalogger/config.py
klimalogger/cpy/__init__.py
klimalogger/cpy/i2c.py
klimalogger/cpy/mqtt.py
klimalogger/cpy/ntp.py
klimalogger/cpy/pixel.py
klimalogger/data_builder.py
klimalogger/logger.py
klimalogger/measurement.py
klimalogger/script/__init__.py
klimalogger/script/klimalogger.py
klimalogger/script/receive_data.py
klimalogger/sensor/__init__.py
klimalogger/sensor/bh1750.py
klimalogger/sensor/bme680.py
klimalogger/sensor/bmp3xx.py
klimalogger/sensor/dps310.py
klimalogger/sensor/mmc56x3.py
klimalogger/sensor/pm25.py
klimalogger/sensor/scd4x.py
klimalogger/sensor/sgp30.py
klimalogger/sensor/sgp40.py
klimalogger/sensor/sht4x.py
klimalogger/sensor/tsl2591.py
klimalogger/sensor/veml7700.py
klimalogger/sensors.py
klimalogger/transport.py
klimalogger-0.8.10.dist-info/METADATA
klimalogger-0.8.10.dist-info/WHEEL
klimalogger-0.8.10.dist-info/entry_points.txt
klimalogger-0.8.10.dist-info/licenses/LICENSE
klimalogger-0.8.10.dist-info/RECORD
