Metadata-Version: 2.4
Name: klimalogger
Version: 0.8.10
Summary: Simple data logging client for InfluxDB/MQTT target
License: Apache-2.0
License-File: LICENSE
Author: Andreas Würl
Author-email: andi@tryb.de
Requires-Python: >=3.10,<4.0
Classifier: License :: OSI Approved :: Apache Software License
Classifier: Programming Language :: Python :: 3
Classifier: Programming Language :: Python :: 3.10
Classifier: Programming Language :: Python :: 3.11
Classifier: Programming Language :: Python :: 3.12
Classifier: Programming Language :: Python :: 3.13
Classifier: Programming Language :: Python :: 3.14
Requires-Dist: adafruit-circuitpython-bh1750 (>=1.1.16,<2.0.0)
Requires-Dist: adafruit-circuitpython-bme680 (>=3.7.13,<4.0.0)
Requires-Dist: adafruit-circuitpython-bmp3xx (>=1.3.24,<2.0.0)
Requires-Dist: adafruit-circuitpython-busdevice (>=5.2,<6.0)
Requires-Dist: adafruit-circuitpython-dps310 (>=2.1.20,<3.0.0)
Requires-Dist: adafruit-circuitpython-mmc56x3 (>=1.0.13,<2.0.0)
Requires-Dist: adafruit-circuitpython-pm25 (>=2.1.22,<3.0.0)
Requires-Dist: adafruit-circuitpython-scd4x (>=1.4.8,<2.0.0)
Requires-Dist: adafruit-circuitpython-sgp30 (>=3.0.13,<4.0.0)
Requires-Dist: adafruit-circuitpython-sgp40 (>=1.3.21,<2.0.0)
Requires-Dist: adafruit-circuitpython-sht4x (>=1.0.24,<2.0.0)
Requires-Dist: adafruit-circuitpython-tsl2591 (>=1.4.5,<2.0.0)
Requires-Dist: adafruit-circuitpython-veml7700 (>=2.1.5,<3.0.0)
Requires-Dist: lazy (>=1.6,<2.0)
Requires-Dist: paho-mqtt (>=2.1.0,<3.0.0)
Project-URL: Bug Tracker, https://github.com/wuan/klimalogger/issues
Project-URL: Homepage, https://github.com/wuan/klimalogger
